psycopg2/__init__.py
psycopg2/_ipaddress.py
psycopg2/_json.py
psycopg2/_lru_cache.py
psycopg2/_range.py
psycopg2/compat.py
psycopg2/errorcodes.py
psycopg2/errors.py
psycopg2/extensions.py
psycopg2/extras.py
psycopg2/pool.py
psycopg2/sql.py
psycopg2/tz.py
aws_psycopg2-1.2.0.dist-info/METADATA
aws_psycopg2-1.2.0.dist-info/WHEEL
aws_psycopg2-1.2.0.dist-info/top_level.txt
aws_psycopg2-1.2.0.dist-info/RECORD
