Metadata-Version: 2.1
Name: aws-psycopg2
Version: 1.2.0
Summary: A aws psycopg2 package from psycopg2.
Home-page: https://github.com/AbhimanyuHK/aws-psycopg2
Author: Abhimanyu HK
Author-email: manyu1994@hotmail.com
License: UNKNOWN
Platform: UNKNOWN
Classifier: Programming Language :: Python :: 3
Classifier: License :: OSI Approved :: MIT License
Classifier: Operating System :: OS Independent
